svgcheck/__init__.py
svgcheck/checksvg.py
svgcheck/log.py
svgcheck/run.py
svgcheck/test.py
svgcheck/word_properties.py
svgcheck-0.11.0.dist-info/licenses/LICENSE
svgcheck-0.11.0.dist-info/METADATA
svgcheck-0.11.0.dist-info/WHEEL
svgcheck-0.11.0.dist-info/entry_points.txt
svgcheck-0.11.0.dist-info/top_level.txt
svgcheck-0.11.0.dist-info/RECORD
