Metadata-Version: 2.4
Name: svgcheck
Version: 0.11.0
Summary: Verify that an svg file is compliant with the RFC standards.
Author-email: IETF Tools <tools-help@ietf.org>
License-Expression: BSD-3-Clause
Project-URL: homepage, https://github.com/ietf-tools/svgcheck
Project-URL: source, https://github.com/ietf-tools/svgcheck
Project-URL: issues, https://github.com/ietf-tools/svgcheck/issues
Project-URL: changelog, https://github.com/ietf-tools/svgcheck/blob/main/CHANGELOG.md
Project-URL: releasenotes, https://github.com/ietf-tools/svgcheck/releases
Keywords: svg,validation,rfc,internet-draft,xml,xml2rfc
Classifier: Development Status :: 5 - Production/Stable
Classifier: Programming Language :: Python :: 3.9
Classifier: Programming Language :: Python :: 3.10
Classifier: Programming Language :: Python :: 3.11
Classifier: Programming Language :: Python :: 3.12
Classifier: Programming Language :: Python :: 3.13
Requires-Python: >=3.9
License-File: LICENSE
Requires-Dist: lxml>=5.3.0
Requires-Dist: xml2rfc>=3.24.0
Provides-Extra: tests
Requires-Dist: coverage; extra == "tests"
Requires-Dist: pycodestyle; extra == "tests"
Requires-Dist: pyflakes>=0.8.1; extra == "tests"
Requires-Dist: tox; extra == "tests"
Dynamic: license-file
